svarcinator_poetry_test/__init__.py
svarcinator_poetry_test/main.py
svarcinator_poetry_test-0.1.0.dist-info/METADATA
svarcinator_poetry_test-0.1.0.dist-info/WHEEL
svarcinator_poetry_test-0.1.0.dist-info/RECORD
