Metadata-Version: 2.1
Name: svarcinator_poetry_test
Version: 0.1.0
Summary: 
Author: Tereza
Author-email: schwarzova.tereza9@gmail.com
Requires-Python: >=3.10,<4.0
Classifier: Programming Language :: Python :: 3
Classifier: Programming Language :: Python :: 3.10
Classifier: Programming Language :: Python :: 3.11
Classifier: Programming Language :: Python :: 3.12
Requires-Dist: pytest (>=8.3.2,<9.0.0)
